LICENSE.txt
MANIFEST.in
README.rst
setup.py
structspec/__init__.py
structspec/common.py
structspec/interfaces.py
structspec/structspec-schema.json
structspec/structspec.py
structspec.egg-info/PKG-INFO
structspec.egg-info/SOURCES.txt
structspec.egg-info/dependency_links.txt
structspec.egg-info/entry_points.txt
structspec.egg-info/requires.txt
structspec.egg-info/top_level.txt
structspec/languages/__init__.py
structspec/languages/c.py
structspec/languages/python.py
structspec/test/__init__.py
structspec/test/test_structspec.py