Metadata-Version: 1.1
Name: structspec
Version: 0.1.2
Summary: Language-independent binary packet structure specification
Home-page: https://github.com/Feneric/structspec
Author: Eric W. Brown
Author-email: UNKNOWN
License: UNKNOWN
Keywords: software development JSON Schema Python JavaScript C C++ Nim
Platform: UNKNOWN
Classifier: Development Status :: 2 - Pre-Alpha
Classifier: Environment :: Console
Classifier: Intended Audience :: Developers
Classifier: License :: OSI Approved :: GNU General Public License v2 (GPLv2)
Classifier: Natural Language :: English
Classifier: Operating System :: MacOS :: MacOS X
Classifier: Operating System :: POSIX
Classifier: Operating System :: Unix
Classifier: Programming Language :: Python
Classifier: Programming Language :: JavaScript
Classifier: Topic :: Software Development
